pathsummary.py
pathsummary-0.1.0a6.dist-info/LICENSE.md
pathsummary-0.1.0a6.dist-info/METADATA
pathsummary-0.1.0a6.dist-info/WHEEL
pathsummary-0.1.0a6.dist-info/entry_points.txt
pathsummary-0.1.0a6.dist-info/top_level.txt
pathsummary-0.1.0a6.dist-info/RECORD
