Metadata-Version: 2.1
Name: pathsummary
Version: 0.1.0a6
Summary: Summarizes the content of a path returning a table.
Home-page: https://gitlab.com/david.scheliga/pathsummary
Author: David Scheliga
License: GNU General Public License V3 (GPLv3)
Project-URL: Documentation, https://pathsummary.readthedocs.io/en/latest/
Project-URL: Source Code Repository, https://gitlab.com/david.scheliga/pathsummary
Platform: UNKNOWN
Classifier: Development Status :: 3 - Alpha
Classifier: License :: OSI Approved :: GNU General Public License v3 (GPLv3)
Classifier: Operating System :: OS Independent
Classifier: Programming Language :: Python :: 3
Classifier: Programming Language :: Python :: 3.6
Classifier: Programming Language :: Python :: 3.7
Classifier: Programming Language :: Python :: 3.8
Classifier: Programming Language :: Python :: 3.9
Requires-Dist: pandas (>=1.0.0)
Requires-Dist: pathwalker (>=0.0.1)
Requires-Dist: click (>=7.2.1)
